accurate_cli/__init__.py
accurate_cli/main.py
accurate_cli-0.2.1.dist-info/METADATA
accurate_cli-0.2.1.dist-info/WHEEL
accurate_cli-0.2.1.dist-info/entry_points.txt
accurate_cli-0.2.1.dist-info/RECORD
