Metadata-Version: 2.1
Name: accurate-cli
Version: 0.2.1
Summary: 
Author: Mattia Consani
Author-email: mattia.consani@epfl.ch
Requires-Python: >=3.11,<4.0
Classifier: Programming Language :: Python :: 3
Classifier: Programming Language :: Python :: 3.11
Classifier: Programming Language :: Python :: 3.12
Requires-Dist: matplotlib (>=3.9.1,<4.0.0)
Requires-Dist: pyserial (>=3.5,<4.0)
Requires-Dist: pyvisa (>=1.14.1,<2.0.0)
Requires-Dist: typer[all] (>=0.12.3,<0.13.0)
